setup.cfg
setup.py
nfcu/__init__.py
nfcu.egg-info/PKG-INFO
nfcu.egg-info/SOURCES.txt
nfcu.egg-info/dependency_links.txt
nfcu.egg-info/top_level.txt
nfcu/exceptions/__init__.py