Metadata-Version: 1.1
Name: nfcu
Version: 0.1.2
Summary: Navy Federal Credit Union Module
Home-page: https://github.com/morissette/nfcu
Author: Matthew Harris
Author-email: matt@x-qa.com
License: UNKNOWN
Download-URL: https://github.com/morissette/nfcu/tarball/0.1.2
Keywords: nfcu,fintech,navy federal,api
Platform: UNKNOWN
